autolint/__init__.py
autolint-0.1.0.dist-info/METADATA
autolint-0.1.0.dist-info/WHEEL
autolint-0.1.0.dist-info/top_level.txt
autolint-0.1.0.dist-info/RECORD
