Metadata-Version: 2.1
Name: autolint
Version: 0.1.0
Summary: Linting tools
Author: AdaCore's IT Team
License: GPLv3
